streamlit_sensors/__init__.py
streamlit_sensors/frontend/index.html
streamlit_sensors/frontend/main.js
streamlit_sensors/frontend/streamlit-component-lib.js
streamlit_sensors/frontend/style.css
streamlit_sensors-0.2.8.dist-info/LICENSE
streamlit_sensors-0.2.8.dist-info/METADATA
streamlit_sensors-0.2.8.dist-info/WHEEL
streamlit_sensors-0.2.8.dist-info/top_level.txt
streamlit_sensors-0.2.8.dist-info/RECORD
