Metadata-Version: 2.1
Name: streamlit-sensors
Version: 0.2.8
Summary: Get geolocation and heading
Author: Valentin Vial
Author-email: valentinvialent@gmail.com
Requires-Python: >=3.7
License-File: LICENSE
Requires-Dist: streamlit >=1.2
Requires-Dist: jinja2
